rest_multi_factor/__init__.py
rest_multi_factor/apps.py
rest_multi_factor/backends.py
rest_multi_factor/containers.py
rest_multi_factor/exceptions.py
rest_multi_factor/fields.py
rest_multi_factor/mixins.py
rest_multi_factor/permissions.py
rest_multi_factor/registry.py
rest_multi_factor/routers.py
rest_multi_factor/throttling.py
rest_multi_factor/urls.py
rest_multi_factor/utils.py
rest_multi_factor/version.py
rest_multi_factor/viewsets.py
rest_multi_factor/algorithms/__init__.py
rest_multi_factor/algorithms/abstract.py
rest_multi_factor/algorithms/hotp.py
rest_multi_factor/algorithms/totp.py
rest_multi_factor/encryption/__init__.py
rest_multi_factor/encryption/abstract.py
rest_multi_factor/encryption/aes.py
rest_multi_factor/factories/__init__.py
rest_multi_factor/factories/auth.py
rest_multi_factor/factories/devices.py
rest_multi_factor/factories/user.py
rest_multi_factor/migrations/__init__.py
rest_multi_factor/models/__init__.py
rest_multi_factor/models/base.py
rest_multi_factor/models/meta.py
rest_multi_factor/models/mixins.py
rest_multi_factor/plugins/__init__.py
rest_multi_factor/plugins/hotp/__init__.py
rest_multi_factor/plugins/hotp/apps.py
rest_multi_factor/plugins/hotp/models.py
rest_multi_factor/plugins/hotp/serializers.py
rest_multi_factor/plugins/hotp/settings.py
rest_multi_factor/plugins/hotp/tests.py
rest_multi_factor/plugins/hotp/migrations/__init__.py
rest_multi_factor/plugins/totp/__init__.py
rest_multi_factor/plugins/totp/apps.py
rest_multi_factor/plugins/totp/models.py
rest_multi_factor/plugins/totp/serializers.py
rest_multi_factor/plugins/totp/settings.py
rest_multi_factor/plugins/totp/tests.py
rest_multi_factor/plugins/totp/migrations/__init__.py
rest_multi_factor/serializers/__init__.py
rest_multi_factor/serializers/device.py
rest_multi_factor/serializers/value.py
rest_multi_factor/serializers/fields/__init__.py
rest_multi_factor/serializers/fields/compat.py
rest_multi_factor/serializers/fields/qrcode.py
rest_multi_factor/settings/__init__.py
rest_multi_factor-1.1b1.dist-info/LICENSE.md
rest_multi_factor-1.1b1.dist-info/METADATA
rest_multi_factor-1.1b1.dist-info/WHEEL
rest_multi_factor-1.1b1.dist-info/top_level.txt
rest_multi_factor-1.1b1.dist-info/RECORD
