Metadata-Version: 2.1
Name: rest-multi-factor
Version: 1.1b1
Summary: Multi factor for django rest framework
Home-page: https://github.com/KENTIVO/rest-multi-factor
Author: Joël Maatkamp
Author-email: joel.maatkamp@kentivo.com
License: MIT
Platform: UNKNOWN
Classifier: Development Status :: 4 - Beta
Classifier: Programming Language :: Python :: 3.5
Classifier: Programming Language :: Python :: 3.6
Classifier: Programming Language :: Python :: 3.7
Classifier: Programming Language :: Python :: 3 :: Only
Classifier: Framework :: Django :: 1.11
Classifier: Framework :: Django :: 2.2
Classifier: Topic :: Security
Classifier: Topic :: Internet :: WWW/HTTP
Classifier: Intended Audience :: Developers
Classifier: License :: OSI Approved :: MIT License
Requires-Dist: django
Requires-Dist: djangorestframework
Requires-Dist: cryptography
Provides-Extra: qr
Requires-Dist: qrcode ; extra == 'qr'
Requires-Dist: pillow ; extra == 'qr'
Provides-Extra: test
Requires-Dist: factory-boy ; extra == 'test'
